Root_to_DataFrame_MT/Root_to_DataFrame_MT.py
Root_to_DataFrame_MT/__init__.py
root_to_dataframe_mt-0.0.1.dist-info/METADATA
root_to_dataframe_mt-0.0.1.dist-info/WHEEL
root_to_dataframe_mt-0.0.1.dist-info/licenses/LICENSE
root_to_dataframe_mt-0.0.1.dist-info/RECORD
