Metadata-Version: 2.1
Name: Root_to_DataFrame_MT
Version: 0.0.1
Summary: Create a class that loads a .root file into pandas DataFrames
Project-URL: Homepage, https://github.com/pypa/sampleproject
Project-URL: Bug Tracker, https://github.com/pypa/sampleproject/issues
Author-email: Lorenzo Principe <lorenzomag@hotmail.it>
License-File: LICENSE
Classifier: License :: OSI Approved :: MIT License
Classifier: Operating System :: OS Independent
Classifier: Programming Language :: Python :: 3
Requires-Python: >=3.7
